{
  "leagueId": "premier-league",
  "clubId": "leicester-city",
  "season": "2016-17",
  "division": "top-flight",
  "squad": [
    {
      "id": "kasper-schmeichel-den",
      "name": "Kasper Schmeichel",
      "nationality": "DEN",
      "broadPosition": "GK",
      "shirtNumber": 1,
      "stats": {
        "appearances": 41,
        "goals": 0
      },
      "seasonRatings": {
        "overall": 81,
        "pace": 43,
        "shooting": 16,
        "passing": 67,
        "dribbling": 52,
        "defending": 60,
        "physical": 75,
        "goalkeeping": 90
      },
      "primeRatings": {
        "overall": 85,
        "pace": 44,
        "shooting": 20,
        "passing": 68,
        "dribbling": 54,
        "defending": 65,
        "physical": 81,
        "goalkeeping": 94
      }
    },
    {
      "id": "luis-hern-ndez-esp",
      "name": "Luis Hernández",
      "nationality": "ESP",
      "broadPosition": "DF",
      "shirtNumber": 2,
      "stats": {
        "appearances": 9,
        "goals": 0
      },
      "seasonRatings": {
        "overall": 56,
        "pace": 53,
        "shooting": 34,
        "passing": 52,
        "dribbling": 44,
        "defending": 62,
        "physical": 57
      },
      "primeRatings": {
        "overall": 77,
        "pace": 72,
        "shooting": 58,
        "passing": 74,
        "dribbling": 66,
        "defending": 85,
        "physical": 78
      }
    },
    {
      "id": "ben-chilwell-eng",
      "name": "Ben Chilwell",
      "nationality": "ENG",
      "broadPosition": "DF",
      "shirtNumber": 3,
      "stats": {
        "appearances": 18,
        "goals": 1
      },
      "seasonRatings": {
        "overall": 62,
        "pace": 55,
        "shooting": 43,
        "passing": 59,
        "dribbling": 50,
        "defending": 69,
        "physical": 67
      },
      "primeRatings": {
        "overall": 83,
        "pace": 81,
        "shooting": 64,
        "passing": 78,
        "dribbling": 72,
        "defending": 92,
        "physical": 87
      }
    },
    {
      "id": "danny-drinkwater-eng",
      "name": "Danny Drinkwater",
      "nationality": "ENG",
      "broadPosition": "MF",
      "shirtNumber": 4,
      "stats": {
        "appearances": 43,
        "goals": 1
      },
      "seasonRatings": {
        "overall": 78,
        "pace": 77,
        "shooting": 71,
        "passing": 81,
        "dribbling": 76,
        "defending": 71,
        "physical": 77
      },
      "primeRatings": {
        "overall": 78,
        "pace": 74,
        "shooting": 70,
        "passing": 81,
        "dribbling": 76,
        "defending": 70,
        "physical": 75
      }
    },
    {
      "id": "wes-morgan-jam",
      "name": "Wes Morgan",
      "nationality": "JAM",
      "broadPosition": "DF",
      "shirtNumber": 5,
      "stats": {
        "appearances": 40,
        "goals": 3
      },
      "seasonRatings": {
        "overall": 74,
        "pace": 68,
        "shooting": 51,
        "passing": 69,
        "dribbling": 64,
        "defending": 85,
        "physical": 77
      },
      "primeRatings": {
        "overall": 80,
        "pace": 77,
        "shooting": 58,
        "passing": 77,
        "dribbling": 71,
        "defending": 89,
        "physical": 85
      }
    },
    {
      "id": "robert-huth-ger",
      "name": "Robert Huth",
      "nationality": "GER",
      "broadPosition": "DF",
      "shirtNumber": 6,
      "stats": {
        "appearances": 43,
        "goals": 2
      },
      "seasonRatings": {
        "overall": 74,
        "pace": 69,
        "shooting": 51,
        "passing": 70,
        "dribbling": 63,
        "defending": 83,
        "physical": 78
      },
      "primeRatings": {
        "overall": 77,
        "pace": 69,
        "shooting": 56,
        "passing": 70,
        "dribbling": 70,
        "defending": 86,
        "physical": 78
      }
    },
    {
      "id": "ahmed-musa-nga",
      "name": "Ahmed Musa",
      "nationality": "NGA",
      "broadPosition": "FW",
      "shirtNumber": 7,
      "stats": {
        "appearances": 30,
        "goals": 4
      },
      "seasonRatings": {
        "overall": 69,
        "pace": 72,
        "shooting": 79,
        "passing": 62,
        "dribbling": 74,
        "defending": 43,
        "physical": 66
      },
      "primeRatings": {
        "overall": 72,
        "pace": 75,
        "shooting": 78,
        "passing": 61,
        "dribbling": 75,
        "defending": 50,
        "physical": 69
      }
    },
    {
      "id": "matty-james-eng",
      "name": "Matty James",
      "nationality": "ENG",
      "broadPosition": "MF",
      "shirtNumber": 8,
      "stats": {
        "appearances": 1,
        "goals": 0
      },
      "seasonRatings": {
        "overall": 48,
        "pace": 46,
        "shooting": 39,
        "passing": 55,
        "dribbling": 48,
        "defending": 39,
        "physical": 44
      },
      "primeRatings": {
        "overall": 70,
        "pace": 68,
        "shooting": 62,
        "passing": 76,
        "dribbling": 72,
        "defending": 62,
        "physical": 66
      }
    },
    {
      "id": "jamie-vardy-eng",
      "name": "Jamie Vardy",
      "nationality": "ENG",
      "broadPosition": "FW",
      "shirtNumber": 9,
      "stats": {
        "appearances": 48,
        "goals": 16
      },
      "seasonRatings": {
        "overall": 83,
        "pace": 88,
        "shooting": 90,
        "passing": 75,
        "dribbling": 88,
        "defending": 58,
        "physical": 77
      },
      "primeRatings": {
        "overall": 86,
        "pace": 89,
        "shooting": 92,
        "passing": 78,
        "dribbling": 87,
        "defending": 62,
        "physical": 81
      }
    },
    {
      "id": "andy-king-wal",
      "name": "Andy King",
      "nationality": "WAL",
      "broadPosition": "MF",
      "shirtNumber": 10,
      "stats": {
        "appearances": 32,
        "goals": 2
      },
      "seasonRatings": {
        "overall": 73,
        "pace": 72,
        "shooting": 66,
        "passing": 81,
        "dribbling": 71,
        "defending": 65,
        "physical": 69
      },
      "primeRatings": {
        "overall": 76,
        "pace": 74,
        "shooting": 68,
        "passing": 82,
        "dribbling": 76,
        "defending": 68,
        "physical": 71
      }
    },
    {
      "id": "marc-albrighton-eng",
      "name": "Marc Albrighton",
      "nationality": "ENG",
      "broadPosition": "MF",
      "shirtNumber": 11,
      "stats": {
        "appearances": 47,
        "goals": 4
      },
      "seasonRatings": {
        "overall": 78,
        "pace": 74,
        "shooting": 70,
        "passing": 83,
        "dribbling": 81,
        "defending": 70,
        "physical": 78
      },
      "primeRatings": {
        "overall": 81,
        "pace": 77,
        "shooting": 71,
        "passing": 88,
        "dribbling": 80,
        "defending": 68,
        "physical": 76
      }
    },
    {
      "id": "ben-hamer-eng",
      "name": "Ben Hamer",
      "nationality": "ENG",
      "broadPosition": "GK",
      "shirtNumber": 12,
      "stats": {
        "appearances": 1,
        "goals": 0
      },
      "seasonRatings": {
        "overall": 48,
        "pace": 45,
        "shooting": 19,
        "passing": 30,
        "dribbling": 15,
        "defending": 27,
        "physical": 41,
        "goalkeeping": 56
      },
      "primeRatings": {
        "overall": 58,
        "pace": 46,
        "shooting": 18,
        "passing": 42,
        "dribbling": 31,
        "defending": 36,
        "physical": 53,
        "goalkeeping": 68
      }
    },
    {
      "id": "daniel-amartey-gha",
      "name": "Daniel Amartey",
      "nationality": "GHA",
      "broadPosition": "MF",
      "shirtNumber": 13,
      "stats": {
        "appearances": 35,
        "goals": 1
      },
      "seasonRatings": {
        "overall": 70,
        "pace": 65,
        "shooting": 63,
        "passing": 78,
        "dribbling": 72,
        "defending": 58,
        "physical": 70
      },
      "primeRatings": {
        "overall": 75,
        "pace": 73,
        "shooting": 69,
        "passing": 77,
        "dribbling": 76,
        "defending": 66,
        "physical": 71
      }
    },
    {
      "id": "bartosz-kapustka-pol",
      "name": "Bartosz Kapustka",
      "nationality": "POL",
      "broadPosition": "MF",
      "shirtNumber": 14,
      "stats": {
        "appearances": 3,
        "goals": 0
      },
      "seasonRatings": {
        "overall": 49,
        "pace": 45,
        "shooting": 41,
        "passing": 54,
        "dribbling": 47,
        "defending": 40,
        "physical": 49
      },
      "primeRatings": {
        "overall": 52,
        "pace": 46,
        "shooting": 44,
        "passing": 55,
        "dribbling": 55,
        "defending": 41,
        "physical": 47
      }
    },
    {
      "id": "jeffrey-schlupp-gha",
      "name": "Jeffrey Schlupp",
      "nationality": "GHA",
      "broadPosition": "DF",
      "shirtNumber": 15,
      "stats": {
        "appearances": 9,
        "goals": 0
      },
      "seasonRatings": {
        "overall": 57,
        "pace": 54,
        "shooting": 40,
        "passing": 53,
        "dribbling": 50,
        "defending": 67,
        "physical": 57
      },
      "primeRatings": {
        "overall": 81,
        "pace": 78,
        "shooting": 59,
        "passing": 78,
        "dribbling": 72,
        "defending": 88,
        "physical": 86
      }
    },
    {
      "id": "danny-simpson-eng",
      "name": "Danny Simpson",
      "nationality": "ENG",
      "broadPosition": "DF",
      "shirtNumber": 17,
      "stats": {
        "appearances": 45,
        "goals": 0
      },
      "seasonRatings": {
        "overall": 76,
        "pace": 74,
        "shooting": 54,
        "passing": 74,
        "dribbling": 66,
        "defending": 83,
        "physical": 80
      },
      "primeRatings": {
        "overall": 84,
        "pace": 80,
        "shooting": 62,
        "passing": 81,
        "dribbling": 72,
        "defending": 93,
        "physical": 87
      }
    },
    {
      "id": "molla-wagu-mli",
      "name": "Molla Wagué",
      "nationality": "MLI",
      "broadPosition": "DF",
      "shirtNumber": 18,
      "stats": {
        "appearances": 1,
        "goals": 0
      },
      "seasonRatings": {
        "overall": 48,
        "pace": 45,
        "shooting": 28,
        "passing": 43,
        "dribbling": 41,
        "defending": 54,
        "physical": 50
      },
      "primeRatings": {
        "overall": 68,
        "pace": 60,
        "shooting": 49,
        "passing": 60,
        "dribbling": 58,
        "defending": 74,
        "physical": 72
      }
    },
    {
      "id": "islam-slimani-alg",
      "name": "Islam Slimani",
      "nationality": "ALG",
      "broadPosition": "FW",
      "shirtNumber": 19,
      "stats": {
        "appearances": 29,
        "goals": 8
      },
      "seasonRatings": {
        "overall": 72,
        "pace": 75,
        "shooting": 78,
        "passing": 64,
        "dribbling": 73,
        "defending": 50,
        "physical": 68
      },
      "primeRatings": {
        "overall": 81,
        "pace": 85,
        "shooting": 88,
        "passing": 73,
        "dribbling": 82,
        "defending": 58,
        "physical": 75
      }
    },
    {
      "id": "shinji-okazaki-jpn",
      "name": "Shinji Okazaki",
      "nationality": "JPN",
      "broadPosition": "FW",
      "shirtNumber": 20,
      "stats": {
        "appearances": 41,
        "goals": 6
      },
      "seasonRatings": {
        "overall": 76,
        "pace": 78,
        "shooting": 86,
        "passing": 66,
        "dribbling": 81,
        "defending": 53,
        "physical": 71
      },
      "primeRatings": {
        "overall": 89,
        "pace": 95,
        "shooting": 96,
        "passing": 82,
        "dribbling": 89,
        "defending": 64,
        "physical": 89
      }
    },
    {
      "id": "ron-robert-zieler-ger",
      "name": "Ron-Robert Zieler",
      "nationality": "GER",
      "broadPosition": "GK",
      "shirtNumber": 21,
      "stats": {
        "appearances": 13,
        "goals": 0
      },
      "seasonRatings": {
        "overall": 55,
        "pace": 43,
        "shooting": 16,
        "passing": 37,
        "dribbling": 28,
        "defending": 38,
        "physical": 52,
        "goalkeeping": 64
      },
      "primeRatings": {
        "overall": 78,
        "pace": 43,
        "shooting": 15,
        "passing": 61,
        "dribbling": 49,
        "defending": 60,
        "physical": 75,
        "goalkeeping": 89
      }
    },
    {
      "id": "demarai-gray-eng",
      "name": "Demarai Gray",
      "nationality": "ENG",
      "broadPosition": "MF",
      "shirtNumber": 22,
      "stats": {
        "appearances": 42,
        "goals": 2
      },
      "seasonRatings": {
        "overall": 76,
        "pace": 74,
        "shooting": 65,
        "passing": 82,
        "dribbling": 74,
        "defending": 65,
        "physical": 75
      },
      "primeRatings": {
        "overall": 83,
        "pace": 82,
        "shooting": 77,
        "passing": 89,
        "dribbling": 85,
        "defending": 75,
        "physical": 83
      }
    },
    {
      "id": "leonardo-ulloa-arg",
      "name": "Leonardo Ulloa",
      "nationality": "ARG",
      "broadPosition": "FW",
      "shirtNumber": 23,
      "stats": {
        "appearances": 23,
        "goals": 1
      },
      "seasonRatings": {
        "overall": 64,
        "pace": 68,
        "shooting": 71,
        "passing": 57,
        "dribbling": 65,
        "defending": 41,
        "physical": 59
      },
      "primeRatings": {
        "overall": 85,
        "pace": 87,
        "shooting": 90,
        "passing": 79,
        "dribbling": 90,
        "defending": 57,
        "physical": 84
      }
    },
    {
      "id": "nampalys-mendy-fra",
      "name": "Nampalys Mendy",
      "nationality": "FRA",
      "broadPosition": "MF",
      "shirtNumber": 24,
      "stats": {
        "appearances": 9,
        "goals": 0
      },
      "seasonRatings": {
        "overall": 55,
        "pace": 49,
        "shooting": 50,
        "passing": 59,
        "dribbling": 53,
        "defending": 46,
        "physical": 50
      },
      "primeRatings": {
        "overall": 73,
        "pace": 72,
        "shooting": 67,
        "passing": 81,
        "dribbling": 75,
        "defending": 61,
        "physical": 69
      }
    },
    {
      "id": "wilfred-ndidi-nga",
      "name": "Wilfred Ndidi",
      "nationality": "NGA",
      "broadPosition": "MF",
      "shirtNumber": 25,
      "stats": {
        "appearances": 22,
        "goals": 3
      },
      "seasonRatings": {
        "overall": 69,
        "pace": 67,
        "shooting": 59,
        "passing": 71,
        "dribbling": 68,
        "defending": 59,
        "physical": 63
      },
      "primeRatings": {
        "overall": 81,
        "pace": 77,
        "shooting": 75,
        "passing": 87,
        "dribbling": 79,
        "defending": 70,
        "physical": 80
      }
    },
    {
      "id": "riyad-mahrez-alg",
      "name": "Riyad Mahrez",
      "nationality": "ALG",
      "broadPosition": "MF",
      "shirtNumber": 26,
      "stats": {
        "appearances": 48,
        "goals": 10
      },
      "seasonRatings": {
        "overall": 85,
        "pace": 83,
        "shooting": 80,
        "passing": 89,
        "dribbling": 83,
        "defending": 76,
        "physical": 81
      },
      "primeRatings": {
        "overall": 87,
        "pace": 85,
        "shooting": 82,
        "passing": 90,
        "dribbling": 88,
        "defending": 76,
        "physical": 83
      }
    },
    {
      "id": "marcin-wasilewski-pol",
      "name": "Marcin Wasilewski",
      "nationality": "POL",
      "broadPosition": "DF",
      "shirtNumber": 27,
      "stats": {
        "appearances": 5,
        "goals": 0
      },
      "seasonRatings": {
        "overall": 51,
        "pace": 45,
        "shooting": 33,
        "passing": 46,
        "dribbling": 38,
        "defending": 61,
        "physical": 57
      },
      "primeRatings": {
        "overall": 72,
        "pace": 64,
        "shooting": 49,
        "passing": 66,
        "dribbling": 62,
        "defending": 78,
        "physical": 74
      }
    },
    {
      "id": "christian-fuchs-aut",
      "name": "Christian Fuchs",
      "nationality": "AUT",
      "broadPosition": "DF",
      "shirtNumber": 28,
      "stats": {
        "appearances": 48,
        "goals": 2
      },
      "seasonRatings": {
        "overall": 76,
        "pace": 68,
        "shooting": 53,
        "passing": 74,
        "dribbling": 68,
        "defending": 82,
        "physical": 79
      },
      "primeRatings": {
        "overall": 79,
        "pace": 73,
        "shooting": 59,
        "passing": 75,
        "dribbling": 66,
        "defending": 88,
        "physical": 81
      }
    },
    {
      "id": "yohan-benalouane-tun",
      "name": "Yohan Benalouane",
      "nationality": "TUN",
      "broadPosition": "DF",
      "shirtNumber": 29,
      "stats": {
        "appearances": 15,
        "goals": 0
      },
      "seasonRatings": {
        "overall": 60,
        "pace": 56,
        "shooting": 38,
        "passing": 54,
        "dribbling": 50,
        "defending": 70,
        "physical": 62
      },
      "primeRatings": {
        "overall": 78,
        "pace": 72,
        "shooting": 55,
        "passing": 72,
        "dribbling": 66,
        "defending": 83,
        "physical": 81
      }
    },
    {
      "id": "elliott-moore-eng",
      "name": "Elliott Moore",
      "nationality": "ENG",
      "broadPosition": "DF",
      "shirtNumber": 36,
      "stats": {
        "appearances": 0,
        "goals": 0
      },
      "seasonRatings": {
        "overall": 45,
        "pace": 38,
        "shooting": 23,
        "passing": 41,
        "dribbling": 36,
        "defending": 53,
        "physical": 47
      },
      "primeRatings": {
        "overall": 48,
        "pace": 44,
        "shooting": 25,
        "passing": 44,
        "dribbling": 40,
        "defending": 57,
        "physical": 51
      }
    },
    {
      "id": "harvey-barnes-eng",
      "name": "Harvey Barnes",
      "nationality": "ENG",
      "broadPosition": "MF",
      "shirtNumber": 39,
      "stats": {
        "appearances": 1,
        "goals": 0
      },
      "seasonRatings": {
        "overall": 48,
        "pace": 43,
        "shooting": 40,
        "passing": 55,
        "dribbling": 47,
        "defending": 36,
        "physical": 46
      },
      "primeRatings": {
        "overall": 89,
        "pace": 88,
        "shooting": 79,
        "passing": 96,
        "dribbling": 86,
        "defending": 80,
        "physical": 83
      }
    }
  ],
  "sourceUrl": "https://en.wikipedia.org/wiki/2016%E2%80%9317_Leicester_City_F.C._season",
  "scrapedAt": "2026-07-08T16:21:17.280Z"
}