{
  "leagueId": "serie-a",
  "clubId": "inter-milan",
  "season": "2022-23",
  "division": "top-flight",
  "squad": [
    {
      "id": "samir-handanovi-svn",
      "name": "Samir Handanović",
      "nationality": "SVN",
      "broadPosition": "GK",
      "shirtNumber": 1,
      "stats": {
        "appearances": 16,
        "goals": 0
      },
      "seasonRatings": {
        "overall": 69,
        "pace": 46,
        "shooting": 15,
        "passing": 53,
        "dribbling": 37,
        "defending": 51,
        "physical": 62,
        "goalkeeping": 80
      },
      "primeRatings": {
        "overall": 87,
        "pace": 44,
        "shooting": 16,
        "passing": 74,
        "dribbling": 57,
        "defending": 69,
        "physical": 82,
        "goalkeeping": 96
      }
    },
    {
      "id": "alex-cordaz-ita",
      "name": "Alex Cordaz",
      "nationality": "ITA",
      "broadPosition": "GK",
      "shirtNumber": 21,
      "stats": {
        "appearances": 1,
        "goals": 0
      },
      "seasonRatings": {
        "overall": 47,
        "pace": 43,
        "shooting": 19,
        "passing": 31,
        "dribbling": 19,
        "defending": 25,
        "physical": 43,
        "goalkeeping": 54
      },
      "primeRatings": {
        "overall": 50,
        "pace": 48,
        "shooting": 16,
        "passing": 37,
        "dribbling": 23,
        "defending": 28,
        "physical": 44,
        "goalkeeping": 59
      }
    },
    {
      "id": "andr-onana-cmr",
      "name": "André Onana",
      "nationality": "CMR",
      "broadPosition": "GK",
      "shirtNumber": 24,
      "stats": {
        "appearances": 41,
        "goals": 0
      },
      "seasonRatings": {
        "overall": 75,
        "pace": 43,
        "shooting": 19,
        "passing": 62,
        "dribbling": 44,
        "defending": 58,
        "physical": 69,
        "goalkeeping": 85
      },
      "primeRatings": {
        "overall": 88,
        "pace": 47,
        "shooting": 18,
        "passing": 72,
        "dribbling": 60,
        "defending": 69,
        "physical": 86,
        "goalkeeping": 97
      }
    },
    {
      "id": "denzel-dumfries-ned",
      "name": "Denzel Dumfries",
      "nationality": "NED",
      "broadPosition": "DF",
      "shirtNumber": 2,
      "stats": {
        "appearances": 51,
        "goals": 2
      },
      "seasonRatings": {
        "overall": 84,
        "pace": 80,
        "shooting": 61,
        "passing": 78,
        "dribbling": 71,
        "defending": 92,
        "physical": 87
      },
      "primeRatings": {
        "overall": 88,
        "pace": 83,
        "shooting": 71,
        "passing": 82,
        "dribbling": 76,
        "defending": 94,
        "physical": 93
      }
    },
    {
      "id": "stefan-de-vrij-ned",
      "name": "Stefan de Vrij",
      "nationality": "NED",
      "broadPosition": "DF",
      "shirtNumber": 6,
      "stats": {
        "appearances": 38,
        "goals": 1
      },
      "seasonRatings": {
        "overall": 74,
        "pace": 66,
        "shooting": 55,
        "passing": 69,
        "dribbling": 65,
        "defending": 82,
        "physical": 77
      },
      "primeRatings": {
        "overall": 89,
        "pace": 86,
        "shooting": 67,
        "passing": 81,
        "dribbling": 77,
        "defending": 99,
        "physical": 93
      }
    },
    {
      "id": "robin-gosens-ger",
      "name": "Robin Gosens",
      "nationality": "GER",
      "broadPosition": "DF",
      "shirtNumber": 8,
      "stats": {
        "appearances": 49,
        "goals": 4
      },
      "seasonRatings": {
        "overall": 84,
        "pace": 81,
        "shooting": 64,
        "passing": 78,
        "dribbling": 72,
        "defending": 92,
        "physical": 86
      },
      "primeRatings": {
        "overall": 87,
        "pace": 82,
        "shooting": 70,
        "passing": 85,
        "dribbling": 77,
        "defending": 96,
        "physical": 88
      }
    },
    {
      "id": "raoul-bellanova-ita",
      "name": "Raoul Bellanova",
      "nationality": "ITA",
      "broadPosition": "DF",
      "shirtNumber": 12,
      "stats": {
        "appearances": 22,
        "goals": 0
      },
      "seasonRatings": {
        "overall": 66,
        "pace": 63,
        "shooting": 46,
        "passing": 60,
        "dribbling": 54,
        "defending": 77,
        "physical": 67
      },
      "primeRatings": {
        "overall": 81,
        "pace": 76,
        "shooting": 60,
        "passing": 79,
        "dribbling": 71,
        "defending": 92,
        "physical": 85
      }
    },
    {
      "id": "francesco-acerbi-ita",
      "name": "Francesco Acerbi",
      "nationality": "ITA",
      "broadPosition": "DF",
      "shirtNumber": 15,
      "stats": {
        "appearances": 49,
        "goals": 1
      },
      "seasonRatings": {
        "overall": 83,
        "pace": 80,
        "shooting": 62,
        "passing": 77,
        "dribbling": 72,
        "defending": 89,
        "physical": 87
      },
      "primeRatings": {
        "overall": 87,
        "pace": 82,
        "shooting": 70,
        "passing": 84,
        "dribbling": 76,
        "defending": 94,
        "physical": 93
      }
    },
    {
      "id": "federico-dimarco-ita",
      "name": "Federico Dimarco",
      "nationality": "ITA",
      "broadPosition": "DF",
      "shirtNumber": 32,
      "stats": {
        "appearances": 50,
        "goals": 6
      },
      "seasonRatings": {
        "overall": 83,
        "pace": 76,
        "shooting": 65,
        "passing": 75,
        "dribbling": 74,
        "defending": 89,
        "physical": 89
      },
      "primeRatings": {
        "overall": 89,
        "pace": 82,
        "shooting": 71,
        "passing": 83,
        "dribbling": 77,
        "defending": 99,
        "physical": 95
      }
    },
    {
      "id": "danilo-d-ambrosio-ita",
      "name": "Danilo D'Ambrosio",
      "nationality": "ITA",
      "broadPosition": "DF",
      "shirtNumber": 33,
      "stats": {
        "appearances": 24,
        "goals": 0
      },
      "seasonRatings": {
        "overall": 66,
        "pace": 59,
        "shooting": 45,
        "passing": 60,
        "dribbling": 55,
        "defending": 76,
        "physical": 67
      },
      "primeRatings": {
        "overall": 88,
        "pace": 82,
        "shooting": 70,
        "passing": 81,
        "dribbling": 78,
        "defending": 98,
        "physical": 92
      }
    },
    {
      "id": "matteo-darmian-ita",
      "name": "Matteo Darmian",
      "nationality": "ITA",
      "broadPosition": "DF",
      "shirtNumber": 36,
      "stats": {
        "appearances": 48,
        "goals": 2
      },
      "seasonRatings": {
        "overall": 81,
        "pace": 74,
        "shooting": 62,
        "passing": 78,
        "dribbling": 71,
        "defending": 87,
        "physical": 83
      },
      "primeRatings": {
        "overall": 87,
        "pace": 82,
        "shooting": 68,
        "passing": 85,
        "dribbling": 79,
        "defending": 98,
        "physical": 88
      }
    },
    {
      "id": "milan-kriniar-svk",
      "name": "Milan Škriniar",
      "nationality": "SVK",
      "broadPosition": "DF",
      "shirtNumber": 37,
      "stats": {
        "appearances": 31,
        "goals": 0
      },
      "seasonRatings": {
        "overall": 72,
        "pace": 69,
        "shooting": 50,
        "passing": 67,
        "dribbling": 61,
        "defending": 80,
        "physical": 77
      },
      "primeRatings": {
        "overall": 86,
        "pace": 82,
        "shooting": 67,
        "passing": 79,
        "dribbling": 78,
        "defending": 96,
        "physical": 86
      }
    },
    {
      "id": "mattia-zanotti-ita",
      "name": "Mattia Zanotti",
      "nationality": "ITA",
      "broadPosition": "DF",
      "shirtNumber": 46,
      "stats": {
        "appearances": 2,
        "goals": 0
      },
      "seasonRatings": {
        "overall": 50,
        "pace": 48,
        "shooting": 28,
        "passing": 48,
        "dribbling": 41,
        "defending": 57,
        "physical": 50
      },
      "primeRatings": {
        "overall": 53,
        "pace": 47,
        "shooting": 34,
        "passing": 49,
        "dribbling": 45,
        "defending": 58,
        "physical": 57
      }
    },
    {
      "id": "alessandro-fontanarosa-ita",
      "name": "Alessandro Fontanarosa",
      "nationality": "ITA",
      "broadPosition": "DF",
      "shirtNumber": 47,
      "stats": {
        "appearances": 0,
        "goals": 0
      },
      "seasonRatings": {
        "overall": 45,
        "pace": 38,
        "shooting": 25,
        "passing": 43,
        "dribbling": 34,
        "defending": 56,
        "physical": 48
      },
      "primeRatings": {
        "overall": 48,
        "pace": 42,
        "shooting": 27,
        "passing": 44,
        "dribbling": 35,
        "defending": 54,
        "physical": 51
      }
    },
    {
      "id": "alessandro-bastoni-ita",
      "name": "Alessandro Bastoni",
      "nationality": "ITA",
      "broadPosition": "DF",
      "shirtNumber": 95,
      "stats": {
        "appearances": 45,
        "goals": 0
      },
      "seasonRatings": {
        "overall": 80,
        "pace": 77,
        "shooting": 59,
        "passing": 77,
        "dribbling": 68,
        "defending": 90,
        "physical": 82
      },
      "primeRatings": {
        "overall": 89,
        "pace": 81,
        "shooting": 68,
        "passing": 85,
        "dribbling": 77,
        "defending": 95,
        "physical": 90
      }
    },
    {
      "id": "roberto-gagliardini-ita",
      "name": "Roberto Gagliardini",
      "nationality": "ITA",
      "broadPosition": "MF",
      "shirtNumber": 5,
      "stats": {
        "appearances": 29,
        "goals": 0
      },
      "seasonRatings": {
        "overall": 67,
        "pace": 64,
        "shooting": 58,
        "passing": 70,
        "dribbling": 69,
        "defending": 57,
        "physical": 62
      },
      "primeRatings": {
        "overall": 81,
        "pace": 76,
        "shooting": 71,
        "passing": 87,
        "dribbling": 79,
        "defending": 68,
        "physical": 77
      }
    },
    {
      "id": "kristjan-asllani-alb",
      "name": "Kristjan Asllani",
      "nationality": "ALB",
      "broadPosition": "MF",
      "shirtNumber": 14,
      "stats": {
        "appearances": 29,
        "goals": 0
      },
      "seasonRatings": {
        "overall": 66,
        "pace": 63,
        "shooting": 59,
        "passing": 71,
        "dribbling": 65,
        "defending": 55,
        "physical": 63
      },
      "primeRatings": {
        "overall": 78,
        "pace": 77,
        "shooting": 70,
        "passing": 80,
        "dribbling": 80,
        "defending": 68,
        "physical": 76
      }
    },
    {
      "id": "hakan-alhano-lu-tur",
      "name": "Hakan Çalhanoğlu",
      "nationality": "TUR",
      "broadPosition": "MF",
      "shirtNumber": 20,
      "stats": {
        "appearances": 49,
        "goals": 4
      },
      "seasonRatings": {
        "overall": 83,
        "pace": 82,
        "shooting": 73,
        "passing": 88,
        "dribbling": 83,
        "defending": 72,
        "physical": 78
      },
      "primeRatings": {
        "overall": 89,
        "pace": 87,
        "shooting": 79,
        "passing": 94,
        "dribbling": 89,
        "defending": 77,
        "physical": 85
      }
    },
    {
      "id": "henrikh-mkhitaryan-arm",
      "name": "Henrikh Mkhitaryan",
      "nationality": "ARM",
      "broadPosition": "MF",
      "shirtNumber": 22,
      "stats": {
        "appearances": 49,
        "goals": 5
      },
      "seasonRatings": {
        "overall": 76,
        "pace": 70,
        "shooting": 68,
        "passing": 80,
        "dribbling": 74,
        "defending": 67,
        "physical": 71
      },
      "primeRatings": {
        "overall": 86,
        "pace": 85,
        "shooting": 81,
        "passing": 93,
        "dribbling": 88,
        "defending": 77,
        "physical": 82
      }
    },
    {
      "id": "nicol-barella-ita",
      "name": "Nicolò Barella",
      "nationality": "ITA",
      "broadPosition": "MF",
      "shirtNumber": 23,
      "stats": {
        "appearances": 52,
        "goals": 9
      },
      "seasonRatings": {
        "overall": 87,
        "pace": 86,
        "shooting": 81,
        "passing": 94,
        "dribbling": 85,
        "defending": 75,
        "physical": 82
      },
      "primeRatings": {
        "overall": 87,
        "pace": 82,
        "shooting": 81,
        "passing": 93,
        "dribbling": 84,
        "defending": 75,
        "physical": 83
      }
    },
    {
      "id": "valent-n-carboni-arg",
      "name": "Valentín Carboni",
      "nationality": "ARG",
      "broadPosition": "MF",
      "shirtNumber": 45,
      "stats": {
        "appearances": 6,
        "goals": 0
      },
      "seasonRatings": {
        "overall": 52,
        "pace": 50,
        "shooting": 46,
        "passing": 54,
        "dribbling": 52,
        "defending": 44,
        "physical": 51
      },
      "primeRatings": {
        "overall": 57,
        "pace": 55,
        "shooting": 50,
        "passing": 60,
        "dribbling": 58,
        "defending": 45,
        "physical": 56
      }
    },
    {
      "id": "marcelo-brozovi-cro",
      "name": "Marcelo Brozović",
      "nationality": "CRO",
      "broadPosition": "MF",
      "shirtNumber": 77,
      "stats": {
        "appearances": 40,
        "goals": 3
      },
      "seasonRatings": {
        "overall": 76,
        "pace": 71,
        "shooting": 65,
        "passing": 80,
        "dribbling": 75,
        "defending": 68,
        "physical": 72
      },
      "primeRatings": {
        "overall": 89,
        "pace": 88,
        "shooting": 84,
        "passing": 95,
        "dribbling": 91,
        "defending": 79,
        "physical": 85
      }
    },
    {
      "id": "edin-d-eko-bih",
      "name": "Edin Džeko",
      "nationality": "BIH",
      "broadPosition": "FW",
      "shirtNumber": 9,
      "stats": {
        "appearances": 52,
        "goals": 14
      },
      "seasonRatings": {
        "overall": 79,
        "pace": 82,
        "shooting": 88,
        "passing": 71,
        "dribbling": 80,
        "defending": 52,
        "physical": 76
      },
      "primeRatings": {
        "overall": 87,
        "pace": 92,
        "shooting": 96,
        "passing": 78,
        "dribbling": 87,
        "defending": 59,
        "physical": 82
      }
    },
    {
      "id": "lautaro-mart-nez-arg",
      "name": "Lautaro Martínez",
      "nationality": "ARG",
      "broadPosition": "FW",
      "shirtNumber": 10,
      "stats": {
        "appearances": 57,
        "goals": 28
      },
      "seasonRatings": {
        "overall": 87,
        "pace": 87,
        "shooting": 94,
        "passing": 82,
        "dribbling": 93,
        "defending": 64,
        "physical": 81
      },
      "primeRatings": {
        "overall": 88,
        "pace": 92,
        "shooting": 96,
        "passing": 83,
        "dribbling": 92,
        "defending": 65,
        "physical": 85
      }
    },
    {
      "id": "joaqu-n-correa-arg",
      "name": "Joaquín Correa",
      "nationality": "ARG",
      "broadPosition": "FW",
      "shirtNumber": 11,
      "stats": {
        "appearances": 41,
        "goals": 4
      },
      "seasonRatings": {
        "overall": 76,
        "pace": 80,
        "shooting": 82,
        "passing": 69,
        "dribbling": 79,
        "defending": 51,
        "physical": 71
      },
      "primeRatings": {
        "overall": 86,
        "pace": 90,
        "shooting": 95,
        "passing": 79,
        "dribbling": 87,
        "defending": 62,
        "physical": 81
      }
    },
    {
      "id": "romelu-lukaku-bel",
      "name": "Romelu Lukaku",
      "nationality": "BEL",
      "broadPosition": "FW",
      "shirtNumber": 90,
      "stats": {
        "appearances": 37,
        "goals": 14
      },
      "seasonRatings": {
        "overall": 76,
        "pace": 80,
        "shooting": 82,
        "passing": 70,
        "dribbling": 78,
        "defending": 53,
        "physical": 73
      },
      "primeRatings": {
        "overall": 87,
        "pace": 90,
        "shooting": 97,
        "passing": 78,
        "dribbling": 90,
        "defending": 60,
        "physical": 85
      }
    }
  ],
  "sourceUrl": "https://en.wikipedia.org/wiki/2022%E2%80%9323_Inter_Milan_season",
  "scrapedAt": "2026-07-08T17:54:07.607Z"
}