{
  "leagueId": "la-liga",
  "clubId": "real-sociedad",
  "season": "2018-19",
  "division": "top-flight",
  "squad": [
    {
      "id": "ger-nimo-rulli-arg",
      "name": "Gerónimo Rulli",
      "nationality": "ARG",
      "broadPosition": "GK",
      "shirtNumber": 1,
      "stats": {
        "appearances": 29,
        "goals": 0
      },
      "seasonRatings": {
        "overall": 70,
        "pace": 47,
        "shooting": 15,
        "passing": 55,
        "dribbling": 42,
        "defending": 50,
        "physical": 64,
        "goalkeeping": 77
      },
      "primeRatings": {
        "overall": 84,
        "pace": 44,
        "shooting": 18,
        "passing": 71,
        "dribbling": 53,
        "defending": 65,
        "physical": 77,
        "goalkeeping": 90
      }
    },
    {
      "id": "miguel-ngel-moy-esp",
      "name": "Miguel Ángel Moyà",
      "nationality": "ESP",
      "broadPosition": "GK",
      "shirtNumber": 13,
      "stats": {
        "appearances": 13,
        "goals": 0
      },
      "seasonRatings": {
        "overall": 59,
        "pace": 47,
        "shooting": 17,
        "passing": 46,
        "dribbling": 27,
        "defending": 39,
        "physical": 51,
        "goalkeeping": 65
      },
      "primeRatings": {
        "overall": 76,
        "pace": 43,
        "shooting": 20,
        "passing": 62,
        "dribbling": 49,
        "defending": 58,
        "physical": 70,
        "goalkeeping": 85
      }
    },
    {
      "id": "joseba-zald-a-esp",
      "name": "Joseba Zaldúa",
      "nationality": "ESP",
      "broadPosition": "DF",
      "shirtNumber": 2,
      "stats": {
        "appearances": 29,
        "goals": 1
      },
      "seasonRatings": {
        "overall": 72,
        "pace": 69,
        "shooting": 50,
        "passing": 68,
        "dribbling": 65,
        "defending": 81,
        "physical": 74
      },
      "primeRatings": {
        "overall": 75,
        "pace": 67,
        "shooting": 56,
        "passing": 68,
        "dribbling": 65,
        "defending": 86,
        "physical": 80
      }
    },
    {
      "id": "diego-llorente-esp",
      "name": "Diego Llorente",
      "nationality": "ESP",
      "broadPosition": "DF",
      "shirtNumber": 3,
      "stats": {
        "appearances": 23,
        "goals": 0
      },
      "seasonRatings": {
        "overall": 65,
        "pace": 58,
        "shooting": 47,
        "passing": 60,
        "dribbling": 54,
        "defending": 74,
        "physical": 66
      },
      "primeRatings": {
        "overall": 79,
        "pace": 71,
        "shooting": 61,
        "passing": 72,
        "dribbling": 67,
        "defending": 89,
        "physical": 85
      }
    },
    {
      "id": "h-ctor-moreno-mex",
      "name": "Héctor Moreno",
      "nationality": "MEX",
      "broadPosition": "DF",
      "shirtNumber": 6,
      "stats": {
        "appearances": 29,
        "goals": 1
      },
      "seasonRatings": {
        "overall": 69,
        "pace": 61,
        "shooting": 50,
        "passing": 63,
        "dribbling": 60,
        "defending": 78,
        "physical": 73
      },
      "primeRatings": {
        "overall": 74,
        "pace": 68,
        "shooting": 53,
        "passing": 67,
        "dribbling": 63,
        "defending": 80,
        "physical": 75
      }
    },
    {
      "id": "aritz-elustondo-esp",
      "name": "Aritz Elustondo",
      "nationality": "ESP",
      "broadPosition": "DF",
      "shirtNumber": 15,
      "stats": {
        "appearances": 29,
        "goals": 1
      },
      "seasonRatings": {
        "overall": 72,
        "pace": 69,
        "shooting": 50,
        "passing": 67,
        "dribbling": 63,
        "defending": 83,
        "physical": 76
      },
      "primeRatings": {
        "overall": 79,
        "pace": 75,
        "shooting": 59,
        "passing": 75,
        "dribbling": 70,
        "defending": 86,
        "physical": 80
      }
    },
    {
      "id": "andoni-gorosabel-esp",
      "name": "Andoni Gorosabel",
      "nationality": "ESP",
      "broadPosition": "DF",
      "shirtNumber": 18,
      "stats": {
        "appearances": 7,
        "goals": 0
      },
      "seasonRatings": {
        "overall": 57,
        "pace": 55,
        "shooting": 35,
        "passing": 50,
        "dribbling": 45,
        "defending": 63,
        "physical": 63
      },
      "primeRatings": {
        "overall": 75,
        "pace": 71,
        "shooting": 55,
        "passing": 68,
        "dribbling": 62,
        "defending": 85,
        "physical": 77
      }
    },
    {
      "id": "th-o-hernandez-fra",
      "name": "Théo Hernandez",
      "nationality": "FRA",
      "broadPosition": "DF",
      "shirtNumber": 19,
      "stats": {
        "appearances": 28,
        "goals": 1
      },
      "seasonRatings": {
        "overall": 74,
        "pace": 71,
        "shooting": 53,
        "passing": 68,
        "dribbling": 64,
        "defending": 83,
        "physical": 77
      },
      "primeRatings": {
        "overall": 87,
        "pace": 85,
        "shooting": 68,
        "passing": 82,
        "dribbling": 75,
        "defending": 95,
        "physical": 87
      }
    },
    {
      "id": "k-vin-rodrigues-por",
      "name": "Kévin Rodrigues",
      "nationality": "POR",
      "broadPosition": "DF",
      "shirtNumber": 20,
      "stats": {
        "appearances": 7,
        "goals": 0
      },
      "seasonRatings": {
        "overall": 54,
        "pace": 51,
        "shooting": 33,
        "passing": 50,
        "dribbling": 45,
        "defending": 59,
        "physical": 56
      },
      "primeRatings": {
        "overall": 66,
        "pace": 61,
        "shooting": 46,
        "passing": 59,
        "dribbling": 53,
        "defending": 72,
        "physical": 69
      }
    },
    {
      "id": "ra-l-navas-esp",
      "name": "Raúl Navas",
      "nationality": "ESP",
      "broadPosition": "DF",
      "shirtNumber": 22,
      "stats": {
        "appearances": 16,
        "goals": 0
      },
      "seasonRatings": {
        "overall": 62,
        "pace": 59,
        "shooting": 40,
        "passing": 57,
        "dribbling": 53,
        "defending": 67,
        "physical": 67
      },
      "primeRatings": {
        "overall": 76,
        "pace": 70,
        "shooting": 58,
        "passing": 71,
        "dribbling": 67,
        "defending": 85,
        "physical": 80
      }
    },
    {
      "id": "robin-le-normand-fra",
      "name": "Robin Le Normand",
      "nationality": "FRA",
      "broadPosition": "DF",
      "shirtNumber": 27,
      "stats": {
        "appearances": 7,
        "goals": 0
      },
      "seasonRatings": {
        "overall": 56,
        "pace": 53,
        "shooting": 34,
        "passing": 51,
        "dribbling": 45,
        "defending": 62,
        "physical": 59
      },
      "primeRatings": {
        "overall": 84,
        "pace": 76,
        "shooting": 63,
        "passing": 78,
        "dribbling": 77,
        "defending": 90,
        "physical": 89
      }
    },
    {
      "id": "aihen-mu-oz-esp",
      "name": "Aihen Muñoz",
      "nationality": "ESP",
      "broadPosition": "DF",
      "shirtNumber": 29,
      "stats": {
        "appearances": 11,
        "goals": 0
      },
      "seasonRatings": {
        "overall": 56,
        "pace": 48,
        "shooting": 34,
        "passing": 50,
        "dribbling": 44,
        "defending": 62,
        "physical": 56
      },
      "primeRatings": {
        "overall": 71,
        "pace": 66,
        "shooting": 53,
        "passing": 64,
        "dribbling": 61,
        "defending": 77,
        "physical": 75
      }
    },
    {
      "id": "lex-sola-esp",
      "name": "Álex Sola",
      "nationality": "ESP",
      "broadPosition": "DF",
      "shirtNumber": 35,
      "stats": {
        "appearances": 1,
        "goals": 0
      },
      "seasonRatings": {
        "overall": 46,
        "pace": 38,
        "shooting": 24,
        "passing": 42,
        "dribbling": 35,
        "defending": 51,
        "physical": 47
      },
      "primeRatings": {
        "overall": 61,
        "pace": 53,
        "shooting": 41,
        "passing": 57,
        "dribbling": 51,
        "defending": 71,
        "physical": 63
      }
    },
    {
      "id": "asier-illarramendi-esp",
      "name": "Asier Illarramendi",
      "nationality": "ESP",
      "broadPosition": "MF",
      "shirtNumber": 4,
      "stats": {
        "appearances": 26,
        "goals": 1
      },
      "seasonRatings": {
        "overall": 70,
        "pace": 67,
        "shooting": 61,
        "passing": 72,
        "dribbling": 69,
        "defending": 62,
        "physical": 69
      },
      "primeRatings": {
        "overall": 84,
        "pace": 82,
        "shooting": 76,
        "passing": 91,
        "dribbling": 82,
        "defending": 75,
        "physical": 84
      }
    },
    {
      "id": "igor-zubeldia-esp",
      "name": "Igor Zubeldia",
      "nationality": "ESP",
      "broadPosition": "MF",
      "shirtNumber": 5,
      "stats": {
        "appearances": 37,
        "goals": 1
      },
      "seasonRatings": {
        "overall": 74,
        "pace": 70,
        "shooting": 68,
        "passing": 77,
        "dribbling": 75,
        "defending": 67,
        "physical": 68
      },
      "primeRatings": {
        "overall": 77,
        "pace": 73,
        "shooting": 69,
        "passing": 80,
        "dribbling": 80,
        "defending": 69,
        "physical": 75
      }
    },
    {
      "id": "mikel-merino-esp",
      "name": "Mikel Merino",
      "nationality": "ESP",
      "broadPosition": "MF",
      "shirtNumber": 8,
      "stats": {
        "appearances": 32,
        "goals": 4
      },
      "seasonRatings": {
        "overall": 77,
        "pace": 74,
        "shooting": 66,
        "passing": 79,
        "dribbling": 78,
        "defending": 68,
        "physical": 72
      },
      "primeRatings": {
        "overall": 85,
        "pace": 85,
        "shooting": 76,
        "passing": 90,
        "dribbling": 86,
        "defending": 74,
        "physical": 79
      }
    },
    {
      "id": "adnan-januzaj-bel",
      "name": "Adnan Januzaj",
      "nationality": "BEL",
      "broadPosition": "MF",
      "shirtNumber": 11,
      "stats": {
        "appearances": 24,
        "goals": 2
      },
      "seasonRatings": {
        "overall": 70,
        "pace": 64,
        "shooting": 64,
        "passing": 75,
        "dribbling": 71,
        "defending": 57,
        "physical": 65
      },
      "primeRatings": {
        "overall": 81,
        "pace": 78,
        "shooting": 75,
        "passing": 88,
        "dribbling": 79,
        "defending": 71,
        "physical": 78
      }
    },
    {
      "id": "rub-n-pardo-esp",
      "name": "Rubén Pardo",
      "nationality": "ESP",
      "broadPosition": "MF",
      "shirtNumber": 14,
      "stats": {
        "appearances": 25,
        "goals": 1
      },
      "seasonRatings": {
        "overall": 70,
        "pace": 69,
        "shooting": 60,
        "passing": 75,
        "dribbling": 70,
        "defending": 58,
        "physical": 66
      },
      "primeRatings": {
        "overall": 76,
        "pace": 74,
        "shooting": 67,
        "passing": 80,
        "dribbling": 78,
        "defending": 67,
        "physical": 72
      }
    },
    {
      "id": "mart-n-merquelanz-esp",
      "name": "Martín Merquelanz",
      "nationality": "ESP",
      "broadPosition": "MF",
      "shirtNumber": 16,
      "stats": {
        "appearances": 1,
        "goals": 0
      },
      "seasonRatings": {
        "overall": 47,
        "pace": 43,
        "shooting": 36,
        "passing": 50,
        "dribbling": 44,
        "defending": 36,
        "physical": 43
      },
      "primeRatings": {
        "overall": 61,
        "pace": 57,
        "shooting": 51,
        "passing": 65,
        "dribbling": 60,
        "defending": 49,
        "physical": 58
      }
    },
    {
      "id": "david-zurutuza-esp",
      "name": "David Zurutuza",
      "nationality": "ESP",
      "broadPosition": "MF",
      "shirtNumber": 17,
      "stats": {
        "appearances": 24,
        "goals": 2
      },
      "seasonRatings": {
        "overall": 71,
        "pace": 69,
        "shooting": 61,
        "passing": 78,
        "dribbling": 72,
        "defending": 63,
        "physical": 68
      },
      "primeRatings": {
        "overall": 78,
        "pace": 78,
        "shooting": 71,
        "passing": 83,
        "dribbling": 76,
        "defending": 68,
        "physical": 73
      }
    },
    {
      "id": "luca-sangalli-esp",
      "name": "Luca Sangalli",
      "nationality": "ESP",
      "broadPosition": "MF",
      "shirtNumber": 23,
      "stats": {
        "appearances": 19,
        "goals": 1
      },
      "seasonRatings": {
        "overall": 65,
        "pace": 64,
        "shooting": 59,
        "passing": 68,
        "dribbling": 68,
        "defending": 57,
        "physical": 61
      },
      "primeRatings": {
        "overall": 69,
        "pace": 64,
        "shooting": 63,
        "passing": 76,
        "dribbling": 68,
        "defending": 60,
        "physical": 67
      }
    },
    {
      "id": "ander-guevara-esp",
      "name": "Ander Guevara",
      "nationality": "ESP",
      "broadPosition": "MF",
      "shirtNumber": 26,
      "stats": {
        "appearances": 1,
        "goals": 0
      },
      "seasonRatings": {
        "overall": 46,
        "pace": 40,
        "shooting": 37,
        "passing": 52,
        "dribbling": 44,
        "defending": 37,
        "physical": 41
      },
      "primeRatings": {
        "overall": 72,
        "pace": 70,
        "shooting": 63,
        "passing": 77,
        "dribbling": 74,
        "defending": 64,
        "physical": 67
      }
    },
    {
      "id": "mart-n-zubimendi-esp",
      "name": "Martín Zubimendi",
      "nationality": "ESP",
      "broadPosition": "MF",
      "shirtNumber": 36,
      "stats": {
        "appearances": 1,
        "goals": 0
      },
      "seasonRatings": {
        "overall": 51,
        "pace": 50,
        "shooting": 44,
        "passing": 57,
        "dribbling": 50,
        "defending": 40,
        "physical": 48
      },
      "primeRatings": {
        "overall": 82,
        "pace": 77,
        "shooting": 77,
        "passing": 84,
        "dribbling": 80,
        "defending": 74,
        "physical": 79
      }
    },
    {
      "id": "juanmi-esp",
      "name": "Juanmi",
      "nationality": "ESP",
      "broadPosition": "FW",
      "shirtNumber": 7,
      "stats": {
        "appearances": 34,
        "goals": 6
      },
      "seasonRatings": {
        "overall": 78,
        "pace": 84,
        "shooting": 84,
        "passing": 71,
        "dribbling": 79,
        "defending": 50,
        "physical": 78
      },
      "primeRatings": {
        "overall": 88,
        "pace": 91,
        "shooting": 95,
        "passing": 81,
        "dribbling": 90,
        "defending": 61,
        "physical": 84
      }
    },
    {
      "id": "mikel-oyarzabal-esp",
      "name": "Mikel Oyarzabal",
      "nationality": "ESP",
      "broadPosition": "FW",
      "shirtNumber": 10,
      "stats": {
        "appearances": 41,
        "goals": 14
      },
      "seasonRatings": {
        "overall": 85,
        "pace": 86,
        "shooting": 96,
        "passing": 76,
        "dribbling": 90,
        "defending": 62,
        "physical": 79
      },
      "primeRatings": {
        "overall": 86,
        "pace": 89,
        "shooting": 91,
        "passing": 75,
        "dribbling": 87,
        "defending": 64,
        "physical": 84
      }
    },
    {
      "id": "willian-jos-bra",
      "name": "Willian José",
      "nationality": "BRA",
      "broadPosition": "FW",
      "shirtNumber": 12,
      "stats": {
        "appearances": 34,
        "goals": 11
      },
      "seasonRatings": {
        "overall": 81,
        "pace": 84,
        "shooting": 88,
        "passing": 72,
        "dribbling": 84,
        "defending": 53,
        "physical": 80
      },
      "primeRatings": {
        "overall": 89,
        "pace": 93,
        "shooting": 97,
        "passing": 78,
        "dribbling": 89,
        "defending": 63,
        "physical": 88
      }
    },
    {
      "id": "jon-bautista-esp",
      "name": "Jon Bautista",
      "nationality": "ESP",
      "broadPosition": "FW",
      "shirtNumber": 21,
      "stats": {
        "appearances": 19,
        "goals": 1
      },
      "seasonRatings": {
        "overall": 63,
        "pace": 67,
        "shooting": 73,
        "passing": 55,
        "dribbling": 63,
        "defending": 40,
        "physical": 57
      },
      "primeRatings": {
        "overall": 69,
        "pace": 71,
        "shooting": 80,
        "passing": 60,
        "dribbling": 71,
        "defending": 47,
        "physical": 64
      }
    },
    {
      "id": "sandro-ram-rez-esp",
      "name": "Sandro Ramírez",
      "nationality": "ESP",
      "broadPosition": "FW",
      "shirtNumber": 24,
      "stats": {
        "appearances": 26,
        "goals": 0
      },
      "seasonRatings": {
        "overall": 65,
        "pace": 69,
        "shooting": 73,
        "passing": 55,
        "dribbling": 67,
        "defending": 37,
        "physical": 63
      },
      "primeRatings": {
        "overall": 73,
        "pace": 77,
        "shooting": 84,
        "passing": 65,
        "dribbling": 74,
        "defending": 47,
        "physical": 72
      }
    },
    {
      "id": "roberto-l-pez-esp",
      "name": "Roberto López",
      "nationality": "ESP",
      "broadPosition": "FW",
      "shirtNumber": 28,
      "stats": {
        "appearances": 1,
        "goals": 0
      },
      "seasonRatings": {
        "overall": 48,
        "pace": 51,
        "shooting": 54,
        "passing": 39,
        "dribbling": 53,
        "defending": 23,
        "physical": 45
      },
      "primeRatings": {
        "overall": 70,
        "pace": 72,
        "shooting": 79,
        "passing": 62,
        "dribbling": 73,
        "defending": 48,
        "physical": 66
      }
    },
    {
      "id": "ander-barrenetxea-esp",
      "name": "Ander Barrenetxea",
      "nationality": "ESP",
      "broadPosition": "FW",
      "shirtNumber": 34,
      "stats": {
        "appearances": 9,
        "goals": 1
      },
      "seasonRatings": {
        "overall": 58,
        "pace": 59,
        "shooting": 68,
        "passing": 50,
        "dribbling": 63,
        "defending": 32,
        "physical": 53
      },
      "primeRatings": {
        "overall": 75,
        "pace": 78,
        "shooting": 81,
        "passing": 68,
        "dribbling": 77,
        "defending": 52,
        "physical": 69
      }
    }
  ],
  "sourceUrl": "https://en.wikipedia.org/wiki/2018%E2%80%9319_Real_Sociedad_season",
  "scrapedAt": "2026-07-08T12:29:13.152Z"
}